{"cameraMode":{"drawMode":0,"name":"Shaded","section":"Shading Mode"},"sceneLighting":true,"audioPlay":false,"sceneViewState":{"showFog":true,"showMaterialUpdate":false,"showSkybox":true,"showFlares":true,"showImageEffects":true,"showParticleSystems":true},"in2DMode":false,"pivot":{"x":0.3506961464881897,"y":0.018472999334335328,"z":-0.7161239385604858},"rotation":{"x":0.6590697765350342,"y":0.049738164991140369,"z":-0.04376181587576866,"w":0.7491768598556519},"size":1.7658698558807374,"orthographic":false}